flappy_claude/__init__.py
flappy_claude/__main__.py
flappy_claude/config.py
flappy_claude/entities.py
flappy_claude/game.py
flappy_claude/ipc.py
flappy_claude/physics.py
flappy_claude/scores.py
flappy_claude/.claude/settings.local.json
flappy_claude-0.1.0.dist-info/METADATA
flappy_claude-0.1.0.dist-info/WHEEL
flappy_claude-0.1.0.dist-info/entry_points.txt
flappy_claude-0.1.0.dist-info/RECORD
