Metadata-Version: 2.4
Name: flappy-claude
Version: 0.1.0
Summary: A terminal Flappy Bird game for Claude Code wait times
Author: Flappy Claude Contributors
License-Expression: MIT
Requires-Python: >=3.11
Provides-Extra: dev
Requires-Dist: pytest>=7.0.0; extra == 'dev'
